[
  {
    "product_id": "8ecd2b44-816e-438e-98f7-ddf2d40bc519",
    "product_name": "Mobile",
    "category": "Fashion",
    "price": 1177
  },
  {
    "product_id": "c65127e9-4371-4cdb-b5c7-738c9a9b3f71",
    "product_name": "Headphones",
    "category": "Home",
    "price": 4468
  },
  {
    "product_id": "f61a3b3c-106f-49b0-b9ac-1fe64fa3e847",
    "product_name": "Shoes",
    "category": "Home",
    "price": 499
  },
  {
    "product_id": "598bf4c7-2199-466f-8403-6838c689f284",
    "product_name": "Laptop",
    "category": "Home",
    "price": 497
  },
  {
    "product_id": "1532e858-86f2-4892-bd05-8b31a53e6607",
    "product_name": "Watch",
    "category": "Home",
    "price": 392
  }
]